openapi_parser/__init__.py
openapi_parser/enumeration.py
openapi_parser/errors.py
openapi_parser/loose_types.py
openapi_parser/parser.py
openapi_parser/py.typed
openapi_parser/resolver.py
openapi_parser/specification.py
openapi_parser/builders/__init__.py
openapi_parser/builders/common.py
openapi_parser/builders/content.py
openapi_parser/builders/external_doc.py
openapi_parser/builders/header.py
openapi_parser/builders/info.py
openapi_parser/builders/oauth_flow.py
openapi_parser/builders/operation.py
openapi_parser/builders/parameter.py
openapi_parser/builders/path.py
openapi_parser/builders/request.py
openapi_parser/builders/response.py
openapi_parser/builders/schema.py
openapi_parser/builders/schemas.py
openapi_parser/builders/security.py
openapi_parser/builders/server.py
openapi_parser/builders/tag.py
tal_openapi3_parser-1.1.20.dist-info/licenses/license.txt
tal_openapi3_parser-1.1.20.dist-info/METADATA
tal_openapi3_parser-1.1.20.dist-info/WHEEL
tal_openapi3_parser-1.1.20.dist-info/top_level.txt
tal_openapi3_parser-1.1.20.dist-info/RECORD
