Metadata-Version: 2.4
Name: tal-openapi3-parser
Version: 1.1.20
Summary: OpenAPI v3 parser
Home-page: https://github.com/manchenkoff/openapi3-parser
Author: Artem Manchenkov
Author-email: artem@manchenkoff.me
License: MIT
Project-URL: Source, https://github.com/manchenkoff/openapi3-parser
Keywords: swagger,python,swagger-parser,openapi3-parser,parser,openapi3,swagger-api
Classifier: Development Status :: 4 - Beta
Classifier: License :: OSI Approved :: MIT License
Classifier: Operating System :: OS Independent
Classifier: Intended Audience :: Developers
Classifier: Programming Language :: Python :: 3.9
Classifier: Programming Language :: Python :: 3.10
Classifier: Programming Language :: Python :: 3.11
Classifier: Programming Language :: Python :: 3.12
Classifier: Topic :: Software Development :: Libraries
License-File: license.txt
Requires-Dist: prance>=23.6.21.0
Requires-Dist: openapi-spec-validator>=0.7.1
Provides-Extra: dev
Requires-Dist: mypy>=1.15.0; extra == "dev"
Requires-Dist: pytest>=8.3.5; extra == "dev"
Dynamic: author
Dynamic: author-email
Dynamic: classifier
Dynamic: home-page
Dynamic: keywords
Dynamic: license
Dynamic: license-file
Dynamic: project-url
Dynamic: provides-extra
Dynamic: requires-dist
Dynamic: summary
